methylink/__init__.py
methylink/append_mod_tags.py
methylink/main.py
methylink/cli/__init__.py
methylink/cli/core.py
methylink/database/__init__.py
methylink/database/crud.py
methylink-0.6.0.dist-info/LICENSE
methylink-0.6.0.dist-info/METADATA
methylink-0.6.0.dist-info/WHEEL
methylink-0.6.0.dist-info/entry_points.txt
methylink-0.6.0.dist-info/top_level.txt
methylink-0.6.0.dist-info/RECORD
