Metadata-Version: 2.1
Name: methylink
Version: 0.6.0
Summary: methylink is a tool to link methylation tags between SAM/BAM files.
Home-page: https://github.com/projectoriented/methylink
Author: Mei Wu
License: MIT
Keywords: methylation nanopore bioinformatics
Classifier: License :: OSI Approved :: MIT License
Classifier: Programming Language :: Python :: 3.9
Classifier: Environment :: Console
Requires-Python: >=3.9.13
License-File: LICENSE
Requires-Dist: click >=8.1.3
Requires-Dist: pysam >=0.21.0
Requires-Dist: pytest
